repipe/__about__.py
repipe/__init__.py
repipe/scripts.py
repipe-0.0.1.dist-info/METADATA
repipe-0.0.1.dist-info/WHEEL
repipe-0.0.1.dist-info/entry_points.txt
repipe-0.0.1.dist-info/licenses/LICENSE.txt
repipe-0.0.1.dist-info/RECORD
