Metadata-Version: 2.1
Name: repipe
Version: 0.0.1
Project-URL: Documentation, https://github.com/unknown/repipe#readme
Project-URL: Issues, https://github.com/unknown/repipe/issues
Project-URL: Source, https://github.com/unknown/repipe
Author-email: henadzit <henadzi@havenservicing.com>
License-Expression: MIT
License-File: LICENSE.txt
Classifier: Development Status :: 4 - Beta
Classifier: Programming Language :: Python
Classifier: Programming Language :: Python :: 3.8
Classifier: Programming Language :: Python :: 3.9
Classifier: Programming Language :: Python :: 3.10
Classifier: Programming Language :: Python :: 3.11
Classifier: Programming Language :: Python :: 3.12
Classifier: Programming Language :: Python :: Implementation :: CPython
Classifier: Programming Language :: Python :: Implementation :: PyPy
Requires-Python: >=3.8
